monitor_controller/__init__.py
monitor_controller/__main__.py
monitor_controller/config.py
monitor_controller/dataclass.py
monitor_controller/devicelistener.py
monitor_controller/eventcontroller.py
monitor_controller/logger.py
tests/__init__.py
tests/test_config.py
tests/test_devicelistener.py
tests/test_eventcontroller.py
tests/test_logger.py
monitor_controller-0.2.0.dist-info/License.txt
monitor_controller-0.2.0.dist-info/METADATA
monitor_controller-0.2.0.dist-info/WHEEL
monitor_controller-0.2.0.dist-info/entry_points.txt
monitor_controller-0.2.0.dist-info/top_level.txt
monitor_controller-0.2.0.dist-info/RECORD
